pycarus/__init__.py
pycarus/benchmarks/__init__.py
pycarus/benchmarks/classification.py
pycarus/benchmarks/pcd/__init__.py
pycarus/benchmarks/pcd/partseg.py
pycarus/benchmarks/pcd/reconstruction.py
pycarus/datasets/__init__.py
pycarus/datasets/completion_3D.py
pycarus/datasets/manifold40.py
pycarus/datasets/modelnet40.py
pycarus/datasets/mvp.py
pycarus/datasets/pcn.py
pycarus/datasets/ply.py
pycarus/datasets/shapenet_corev2.py
pycarus/datasets/shapenet_part.py
pycarus/datasets/utils.py
pycarus/geometry/__init__.py
pycarus/geometry/mesh.py
pycarus/geometry/pcd.py
pycarus/install_cuda_ext.sh
pycarus/install_torch.sh
pycarus/learning/__init__.py
pycarus/learning/models/__init__.py
pycarus/learning/models/atlasnet_decoder.py
pycarus/learning/models/dgcnn.py
pycarus/learning/models/pcn.py
pycarus/learning/models/pointnet.py
pycarus/learning/models/pointnet2.py
pycarus/learning/models/pointnet2_utils.py
pycarus/learning/models/pointset_generator.py
pycarus/learning/models/siren.py
pycarus/metrics/__init__.py
pycarus/metrics/chamfer_distance.py
pycarus/metrics/emd_distance.py
pycarus/metrics/external/chamfer_cuda.py
pycarus/metrics/external/chamfer_cuda_cpp.cpp
pycarus/metrics/external/chamfer_cuda_cu.cu
pycarus/metrics/external/emd_cuda.py
pycarus/metrics/external/emd_cuda_cpp.cpp
pycarus/metrics/external/emd_cuda_cu.cu
pycarus/metrics/external/setup_chamfer_cuda.py
pycarus/metrics/external/setup_emd_cuda.py
pycarus/metrics/f_score.py
pycarus/metrics/metric.py
pycarus/metrics/partseg_iou.py
pycarus/py.typed
pycarus/transforms/__init__.py
pycarus/transforms/pcd.py
pycarus/transforms/var.py
pycarus/utils.py
pycarus/wheels/emdcuda-0.0.0-cp38-cp38-linux_x86_64.whl
pycarus-0.7.8.dist-info/METADATA
pycarus-0.7.8.dist-info/WHEEL
pycarus-0.7.8.dist-info/RECORD
