Metadata-Version: 2.1
Name: pycarus
Version: 0.7.8
Summary: Utilities for computer vision and 3D geometry
Author: Luca De Luigi
Author-email: lucadeluigi91@gmail.com
Requires-Python: >=3.8,<3.9.0
Classifier: Programming Language :: Python :: 3
Classifier: Programming Language :: Python :: 3.8
Requires-Dist: einops (>=0.4,<0.5)
Requires-Dist: h5py (>=3.1.0,<4.0.0)
Requires-Dist: ninja (>=1.10.0,<2.0.0)
Requires-Dist: open3d (>=0.15,<0.16)
Requires-Dist: pykdtree (>=1.3.4,<2.0.0)
Requires-Dist: scikit-image (>=0.19,<0.20)
Requires-Dist: torch-geometric (>=2.0.2,<3.0.0)
Requires-Dist: types-setuptools (>=57.0.0,<58.0.0)
